hfile/__init__.py
hfile/cli.py
hfile/filterbymtime.py
hfile/removefile.py
hfile/walkdirectory.py
hfile-1.0.8.dist-info/DESCRIPTION.rst
hfile-1.0.8.dist-info/METADATA
hfile-1.0.8.dist-info/RECORD
hfile-1.0.8.dist-info/WHEEL
hfile-1.0.8.dist-info/entry_points.txt
hfile-1.0.8.dist-info/metadata.json
hfile-1.0.8.dist-info/top_level.txt
